{
	"name" : "human:rooms",
	"rooms" : [
		{"level" : [0, 1, 2, 3, 4], "type" : "random", "name" : "BRICK", "weight" : 2},
		{"level": [0, 1, 2, 3], "type" : "secret", "name" : "SMITH", "count" : 1},
		{"level": [0, 1, 2], "type" : "secret", "name" : "BEDROOM", "count" : 1},
		{"level": [0, 1, 2], "type" : "secret", "name" : "BTEAM", "count" : 1},
		{"level" : [2, 4], "type" : "single", "name" : "TREETHO"},
		{"level" : [0, 1, 2, 3, 4], "type" : "random", "name" : "MESS", "weight" : 2},
		{"level" : [0, 1, 2, 3, 4], "type" : "random", "name" : "PRISON", "weight" : 2},
		{"level" : [0, 1, 2], "type" : "single", "name" : "LIBRARY"},	
		{"level" : [0, 1, 2, 3, 4], "type" : "single", "name" : "ENIKO"},
		{"level" : [0, 1, 2, 3, 4], "type" : "random", "name" : "PIT", "weight" : 1},
		{"level" : [0, 1, 2, 3, 4], "type" : "random", "name" : "STORAGE", "weight" : 2},	
		{"level" : [0, 2, 4], "type" : "single", "name" : "SLIME"},
		{"level" : [0, 2, 4], "type" : "random", "name" : "CREEPER", "weight" : 1},
		{"level" : [4], "type" : "single", "name" : "OBSIDIAN"},
		{"level" : [2, 4], "type" : "single", "name" : "DARKHALL"},
		{"level" : [4], "type" : "single", "name" : "NETHER"},
		{"level" : [4], "type" : "single", "name" : "NETHERFORT"},
		{"level" : [3, 4], "type" : "random", "name" : "SPIDER", "weight" : 1},
		{"level" : [4], "type" : "single", "name" : "BLAZE"},
		{"level" : [0], "type" : "single", "name" : "FIREWORK"}
	]
}